{
    "updatedAt": "2026-04-24T13:00:05.708224703Z",
    "dataCount": 4,
    "temperatures": [
        {
            "site": "SEONYU",
            "temperature": 17.6,
            "measuredAt": "2026-04-24T12:00:00Z",
            "weather": {
                "code": 800,
                "description": "맑음",
                "icon": "01n",
                "temperature": {
                    "actual": 12.06,
                    "feelsLike": 10.73
                },
                "pressure": 1018,
                "humidity": 54,
                "visibility": 10000,
                "windSpeed": 2.06,
                "windDirection": 300,
                "sunrise": 1776977167,
                "sunset": 1777025687
            }
        },
        {
            "site": "ANYANGCHEON",
            "temperature": 22.4,
            "measuredAt": "2026-04-24T12:00:00Z",
            "weather": {
                "code": 800,
                "description": "맑음",
                "icon": "01n",
                "temperature": {
                    "actual": 16.82,
                    "feelsLike": 15.37
                },
                "pressure": 1018,
                "humidity": 31,
                "visibility": 10000,
                "windSpeed": 1.03,
                "windDirection": 350,
                "sunrise": 1776977174,
                "sunset": 1777025669
            }
        },
        {
            "site": "JUNGNANGCHEON",
            "temperature": 21.4,
            "measuredAt": "2026-04-24T12:00:00Z",
            "weather": {
                "code": 800,
                "description": "맑음",
                "icon": "01n",
                "temperature": {
                    "actual": 17.03,
                    "feelsLike": 15.6
                },
                "pressure": 1018,
                "humidity": 31,
                "visibility": 10000,
                "windSpeed": 1.03,
                "windDirection": 350,
                "sunrise": 1776977122,
                "sunset": 1777025650
            }
        },
        {
            "site": "TANCHEON",
            "temperature": 0.0,
            "measuredAt": "2026-04-24T12:00:00Z",
            "weather": {
                "code": 800,
                "description": "맑음",
                "icon": "01n",
                "temperature": {
                    "actual": 17.06,
                    "feelsLike": 15.63
                },
                "pressure": 1018,
                "humidity": 31,
                "visibility": 10000,
                "windSpeed": 1.03,
                "windDirection": 350,
                "sunrise": 1776977130,
                "sunset": 1777025645
            }
        }
    ]
}