{
    "updatedAt": "2026-06-12T12:00:07.241998769Z",
    "dataCount": 4,
    "temperatures": [
        {
            "site": "SEONYU",
            "temperature": 24.4,
            "measuredAt": "2026-06-12T11:00:00Z",
            "weather": {
                "code": 800,
                "description": "맑음",
                "icon": "01n",
                "temperature": {
                    "actual": 22.57,
                    "feelsLike": 22.21
                },
                "pressure": 1013,
                "humidity": 51,
                "visibility": 10000,
                "windSpeed": 2.71,
                "windDirection": 241,
                "sunrise": 1781208646,
                "sunset": 1781261622
            }
        },
        {
            "site": "ANYANGCHEON",
            "temperature": 28.4,
            "measuredAt": "2026-06-12T11:00:00Z",
            "weather": {
                "code": 800,
                "description": "맑음",
                "icon": "01n",
                "temperature": {
                    "actual": 21.58,
                    "feelsLike": 21.2
                },
                "pressure": 1013,
                "humidity": 54,
                "visibility": 10000,
                "windSpeed": 2.3,
                "windDirection": 251,
                "sunrise": 1781208664,
                "sunset": 1781261591
            }
        },
        {
            "site": "JUNGNANGCHEON",
            "temperature": 26.5,
            "measuredAt": "2026-06-12T11:00:00Z",
            "weather": {
                "code": 800,
                "description": "맑음",
                "icon": "01n",
                "temperature": {
                    "actual": 21.88,
                    "feelsLike": 21.43
                },
                "pressure": 1013,
                "humidity": 50,
                "visibility": 10000,
                "windSpeed": 2.19,
                "windDirection": 248,
                "sunrise": 1781208597,
                "sunset": 1781261589
            }
        },
        {
            "site": "TANCHEON",
            "temperature": 26.8,
            "measuredAt": "2026-06-12T11:00:00Z",
            "weather": {
                "code": 800,
                "description": "맑음",
                "icon": "01n",
                "temperature": {
                    "actual": 21.87,
                    "feelsLike": 21.44
                },
                "pressure": 1013,
                "humidity": 51,
                "visibility": 10000,
                "windSpeed": 2.28,
                "windDirection": 250,
                "sunrise": 1781208611,
                "sunset": 1781261579
            }
        }
    ]
}