{
    "updatedAt": "2026-05-13T21:00:03.633364260Z",
    "dataCount": 4,
    "temperatures": [
        {
            "site": "SEONYU",
            "temperature": 0.0,
            "measuredAt": "2026-05-13T20:00:00Z",
            "weather": {
                "code": 804,
                "description": "온흐림",
                "icon": "04d",
                "temperature": {
                    "actual": 17.79,
                    "feelsLike": 17.17
                },
                "pressure": 1012,
                "humidity": 59,
                "visibility": 10000,
                "windSpeed": 0.76,
                "windDirection": 68,
                "sunrise": 1778703874,
                "sunset": 1778754785
            }
        },
        {
            "site": "ANYANGCHEON",
            "temperature": 20.9,
            "measuredAt": "2026-05-13T20:00:00Z",
            "weather": {
                "code": 804,
                "description": "온흐림",
                "icon": "04d",
                "temperature": {
                    "actual": 16.96,
                    "feelsLike": 16.33
                },
                "pressure": 1012,
                "humidity": 62,
                "visibility": 10000,
                "windSpeed": 0.6,
                "windDirection": 85,
                "sunrise": 1778703885,
                "sunset": 1778754760
            }
        },
        {
            "site": "JUNGNANGCHEON",
            "temperature": 24.0,
            "measuredAt": "2026-05-13T20:00:00Z",
            "weather": {
                "code": 804,
                "description": "온흐림",
                "icon": "04d",
                "temperature": {
                    "actual": 17.36,
                    "feelsLike": 16.72
                },
                "pressure": 1013,
                "humidity": 60,
                "visibility": 10000,
                "windSpeed": 1.08,
                "windDirection": 80,
                "sunrise": 1778703825,
                "sunset": 1778754749
            }
        },
        {
            "site": "TANCHEON",
            "temperature": 21.6,
            "measuredAt": "2026-05-13T20:00:00Z",
            "weather": {
                "code": 804,
                "description": "온흐림",
                "icon": "04d",
                "temperature": {
                    "actual": 17.37,
                    "feelsLike": 16.73
                },
                "pressure": 1013,
                "humidity": 60,
                "visibility": 10000,
                "windSpeed": 1.04,
                "windDirection": 81,
                "sunrise": 1778703836,
                "sunset": 1778754742
            }
        }
    ]
}