{
    "updatedAt": "2026-03-18T22:00:01.186303347Z",
    "dataCount": 4,
    "temperatures": [
        {
            "site": "SEONYU",
            "temperature": 9.6,
            "measuredAt": "2026-03-18T21:00:00Z",
            "weather": {
                "code": 800,
                "description": "맑음",
                "icon": "01d",
                "temperature": {
                    "actual": -0.94,
                    "feelsLike": -0.94
                },
                "pressure": 1019,
                "humidity": 69,
                "visibility": 10000,
                "windSpeed": 1.03,
                "windDirection": 280,
                "sunrise": 1773869902,
                "sunset": 1773913337
            }
        },
        {
            "site": "ANYANGCHEON",
            "temperature": 10.7,
            "measuredAt": "2026-03-18T21:00:00Z",
            "weather": {
                "code": 800,
                "description": "맑음",
                "icon": "01d",
                "temperature": {
                    "actual": -0.43,
                    "feelsLike": -0.43
                },
                "pressure": 1018,
                "humidity": 69,
                "visibility": 10000,
                "windSpeed": 1.03,
                "windDirection": 360,
                "sunrise": 1773869896,
                "sunset": 1773913332
            }
        },
        {
            "site": "JUNGNANGCHEON",
            "temperature": 10.4,
            "measuredAt": "2026-03-18T21:00:00Z",
            "weather": {
                "code": 800,
                "description": "맑음",
                "icon": "01d",
                "temperature": {
                    "actual": -0.04,
                    "feelsLike": -0.04
                },
                "pressure": 1018,
                "humidity": 69,
                "visibility": 10000,
                "windSpeed": 1.03,
                "windDirection": 360,
                "sunrise": 1773869861,
                "sunset": 1773913296
            }
        },
        {
            "site": "TANCHEON",
            "temperature": 11.4,
            "measuredAt": "2026-03-18T21:00:00Z",
            "weather": {
                "code": 800,
                "description": "맑음",
                "icon": "01d",
                "temperature": {
                    "actual": 0.06,
                    "feelsLike": 0.06
                },
                "pressure": 1018,
                "humidity": 69,
                "visibility": 10000,
                "windSpeed": 1.03,
                "windDirection": 360,
                "sunrise": 1773869863,
                "sunset": 1773913298
            }
        }
    ]
}