{
    "updatedAt": "2026-06-15T12:59:56.705157458Z",
    "dataCount": 4,
    "temperatures": [
        {
            "site": "SEONYU",
            "temperature": 25.3,
            "measuredAt": "2026-06-15T12:00:00Z",
            "weather": {
                "code": 804,
                "description": "온흐림",
                "icon": "04n",
                "temperature": {
                    "actual": 27.21,
                    "feelsLike": 26.92
                },
                "pressure": 1014,
                "humidity": 38,
                "visibility": 10000,
                "windSpeed": 1.4,
                "windDirection": 326,
                "sunrise": 1781467842,
                "sunset": 1781520897
            }
        },
        {
            "site": "ANYANGCHEON",
            "temperature": 28.7,
            "measuredAt": "2026-06-15T12:00:00Z",
            "weather": {
                "code": 804,
                "description": "온흐림",
                "icon": "04n",
                "temperature": {
                    "actual": 26.42,
                    "feelsLike": 26.42
                },
                "pressure": 1014,
                "humidity": 38,
                "visibility": 10000,
                "windSpeed": 1.22,
                "windDirection": 316,
                "sunrise": 1781467861,
                "sunset": 1781520866
            }
        },
        {
            "site": "JUNGNANGCHEON",
            "temperature": 28.0,
            "measuredAt": "2026-06-15T12:00:00Z",
            "weather": {
                "code": 804,
                "description": "온흐림",
                "icon": "04n",
                "temperature": {
                    "actual": 25.83,
                    "feelsLike": 25.64
                },
                "pressure": 1014,
                "humidity": 45,
                "visibility": 10000,
                "windSpeed": 1.17,
                "windDirection": 329,
                "sunrise": 1781467793,
                "sunset": 1781520864
            }
        },
        {
            "site": "TANCHEON",
            "temperature": 27.7,
            "measuredAt": "2026-06-15T12:00:00Z",
            "weather": {
                "code": 804,
                "description": "온흐림",
                "icon": "04n",
                "temperature": {
                    "actual": 26.05,
                    "feelsLike": 26.05
                },
                "pressure": 1014,
                "humidity": 43,
                "visibility": 10000,
                "windSpeed": 1.01,
                "windDirection": 316,
                "sunrise": 1781467807,
                "sunset": 1781520854
            }
        }
    ]
}