{
    "updatedAt": "2026-04-24T04:00:03.279947949Z",
    "dataCount": 4,
    "temperatures": [
        {
            "site": "SEONYU",
            "temperature": 17.2,
            "measuredAt": "2026-04-24T03:00:00Z",
            "weather": {
                "code": 800,
                "description": "맑음",
                "icon": "01d",
                "temperature": {
                    "actual": 23.05,
                    "feelsLike": 22.01
                },
                "pressure": 1016,
                "humidity": 23,
                "visibility": 10000,
                "windSpeed": 1.54,
                "windDirection": 220,
                "sunrise": 1776977169,
                "sunset": 1777025688
            }
        },
        {
            "site": "ANYANGCHEON",
            "temperature": 21.0,
            "measuredAt": "2026-04-24T03:00:00Z",
            "weather": {
                "code": 801,
                "description": "약간의 구름이 낀 하늘",
                "icon": "02d",
                "temperature": {
                    "actual": 21.3,
                    "feelsLike": 20.09
                },
                "pressure": 1016,
                "humidity": 23,
                "visibility": 10000,
                "windSpeed": 1.03,
                "windDirection": 270,
                "sunrise": 1776977174,
                "sunset": 1777025669
            }
        },
        {
            "site": "JUNGNANGCHEON",
            "temperature": 18.2,
            "measuredAt": "2026-04-24T03:00:00Z",
            "weather": {
                "code": 801,
                "description": "약간의 구름이 낀 하늘",
                "icon": "02d",
                "temperature": {
                    "actual": 21.07,
                    "feelsLike": 19.83
                },
                "pressure": 1016,
                "humidity": 23,
                "visibility": 10000,
                "windSpeed": 1.03,
                "windDirection": 270,
                "sunrise": 1776977123,
                "sunset": 1777025651
            }
        },
        {
            "site": "TANCHEON",
            "temperature": 0.0,
            "measuredAt": "2026-04-24T03:00:00Z",
            "weather": {
                "code": 801,
                "description": "약간의 구름이 낀 하늘",
                "icon": "02d",
                "temperature": {
                    "actual": 21.18,
                    "feelsLike": 19.95
                },
                "pressure": 1016,
                "humidity": 23,
                "visibility": 10000,
                "windSpeed": 1.03,
                "windDirection": 270,
                "sunrise": 1776977130,
                "sunset": 1777025645
            }
        }
    ]
}