{
    "updatedAt": "2026-05-04T13:00:03.662676129Z",
    "dataCount": 4,
    "temperatures": [
        {
            "site": "SEONYU",
            "temperature": 18.3,
            "measuredAt": "2026-05-04T12:00:00Z",
            "weather": {
                "code": 800,
                "description": "맑음",
                "icon": "01n",
                "temperature": {
                    "actual": 14.77,
                    "feelsLike": 13.4
                },
                "pressure": 1018,
                "humidity": 42,
                "visibility": 10000,
                "windSpeed": 2.32,
                "windDirection": 241,
                "sunrise": 1777840459,
                "sunset": 1777890241
            }
        },
        {
            "site": "ANYANGCHEON",
            "temperature": 20.5,
            "measuredAt": "2026-05-04T12:00:00Z",
            "weather": {
                "code": 800,
                "description": "맑음",
                "icon": "01n",
                "temperature": {
                    "actual": 13.6,
                    "feelsLike": 12.35
                },
                "pressure": 1018,
                "humidity": 51,
                "visibility": 10000,
                "windSpeed": 2.26,
                "windDirection": 234,
                "sunrise": 1777840469,
                "sunset": 1777890219
            }
        },
        {
            "site": "JUNGNANGCHEON",
            "temperature": 20.2,
            "measuredAt": "2026-05-04T12:00:00Z",
            "weather": {
                "code": 800,
                "description": "맑음",
                "icon": "01n",
                "temperature": {
                    "actual": 14.45,
                    "feelsLike": 12.97
                },
                "pressure": 1018,
                "humidity": 39,
                "visibility": 10000,
                "windSpeed": 1.95,
                "windDirection": 230,
                "sunrise": 1777840413,
                "sunset": 1777890205
            }
        },
        {
            "site": "TANCHEON",
            "temperature": 20.2,
            "measuredAt": "2026-05-04T12:00:00Z",
            "weather": {
                "code": 800,
                "description": "맑음",
                "icon": "01n",
                "temperature": {
                    "actual": 14.32,
                    "feelsLike": 12.88
                },
                "pressure": 1018,
                "humidity": 41,
                "visibility": 10000,
                "windSpeed": 2.11,
                "windDirection": 227,
                "sunrise": 1777840422,
                "sunset": 1777890199
            }
        }
    ]
}