{
    "updatedAt": "2026-04-03T00:59:59.211708561Z",
    "dataCount": 4,
    "temperatures": [
        {
            "site": "SEONYU",
            "temperature": 14.3,
            "measuredAt": "2026-04-03T00:00:00Z",
            "weather": {
                "code": 721,
                "description": "연무",
                "icon": "50d",
                "temperature": {
                    "actual": 11.06,
                    "feelsLike": 10.08
                },
                "pressure": 1016,
                "humidity": 71,
                "visibility": 3000,
                "windSpeed": 2.06,
                "windDirection": 140,
                "sunrise": 1775164533,
                "sunset": 1775210145
            }
        },
        {
            "site": "ANYANGCHEON",
            "temperature": 14.3,
            "measuredAt": "2026-04-03T00:00:00Z",
            "weather": {
                "code": 721,
                "description": "연무",
                "icon": "50d",
                "temperature": {
                    "actual": 10.81,
                    "feelsLike": 9.57
                },
                "pressure": 1016,
                "humidity": 62,
                "visibility": 4800,
                "windSpeed": 2.57,
                "windDirection": 220,
                "sunrise": 1775164533,
                "sunset": 1775210133
            }
        },
        {
            "site": "JUNGNANGCHEON",
            "temperature": 14.8,
            "measuredAt": "2026-04-03T00:00:00Z",
            "weather": {
                "code": 721,
                "description": "연무",
                "icon": "50d",
                "temperature": {
                    "actual": 11.02,
                    "feelsLike": 9.8
                },
                "pressure": 1016,
                "humidity": 62,
                "visibility": 4800,
                "windSpeed": 2.57,
                "windDirection": 220,
                "sunrise": 1775164491,
                "sunset": 1775210106
            }
        },
        {
            "site": "TANCHEON",
            "temperature": 14.5,
            "measuredAt": "2026-04-03T00:00:00Z",
            "weather": {
                "code": 721,
                "description": "연무",
                "icon": "50d",
                "temperature": {
                    "actual": 11.12,
                    "feelsLike": 9.91
                },
                "pressure": 1016,
                "humidity": 62,
                "visibility": 4800,
                "windSpeed": 2.57,
                "windDirection": 220,
                "sunrise": 1775164495,
                "sunset": 1775210104
            }
        }
    ]
}