{
    "updatedAt": "2026-05-02T15:00:01.556205661Z",
    "dataCount": 4,
    "temperatures": [
        {
            "site": "SEONYU",
            "temperature": 18.5,
            "measuredAt": "2026-05-02T14:00:00Z",
            "weather": {
                "code": 500,
                "description": "실 비",
                "icon": "10n",
                "temperature": {
                    "actual": 16.55,
                    "feelsLike": 16.06
                },
                "pressure": 1010,
                "humidity": 69,
                "visibility": 10000,
                "windSpeed": 4.26,
                "windDirection": 233,
                "sunrise": 1777754124,
                "sunset": 1777803786
            }
        },
        {
            "site": "ANYANGCHEON",
            "temperature": 20.0,
            "measuredAt": "2026-05-02T14:00:00Z",
            "weather": {
                "code": 501,
                "description": "보통 비",
                "icon": "10n",
                "temperature": {
                    "actual": 16.18,
                    "feelsLike": 15.66
                },
                "pressure": 1010,
                "humidity": 69,
                "visibility": 10000,
                "windSpeed": 5.03,
                "windDirection": 228,
                "sunrise": 1777754134,
                "sunset": 1777803764
            }
        },
        {
            "site": "JUNGNANGCHEON",
            "temperature": 20.5,
            "measuredAt": "2026-05-02T14:00:00Z",
            "weather": {
                "code": 500,
                "description": "실 비",
                "icon": "10n",
                "temperature": {
                    "actual": 16.58,
                    "feelsLike": 16.02
                },
                "pressure": 1010,
                "humidity": 66,
                "visibility": 10000,
                "windSpeed": 3.05,
                "windDirection": 238,
                "sunrise": 1777754078,
                "sunset": 1777803750
            }
        },
        {
            "site": "TANCHEON",
            "temperature": 20.4,
            "measuredAt": "2026-05-02T14:00:00Z",
            "weather": {
                "code": 500,
                "description": "실 비",
                "icon": "10n",
                "temperature": {
                    "actual": 16.78,
                    "feelsLike": 16.24
                },
                "pressure": 1010,
                "humidity": 66,
                "visibility": 10000,
                "windSpeed": 3.48,
                "windDirection": 239,
                "sunrise": 1777754088,
                "sunset": 1777803744
            }
        }
    ]
}