{
    "updatedAt": "2026-05-16T12:00:06.765260065Z",
    "dataCount": 4,
    "temperatures": [
        {
            "site": "SEONYU",
            "temperature": 0.0,
            "measuredAt": "2026-05-16T11:00:00Z",
            "weather": {
                "code": 803,
                "description": "튼구름",
                "icon": "04n",
                "temperature": {
                    "actual": 20.27,
                    "feelsLike": 19.55
                },
                "pressure": 1020,
                "humidity": 46,
                "visibility": 10000,
                "windSpeed": 1.35,
                "windDirection": 250,
                "sunrise": 1778876571,
                "sunset": 1778927690
            }
        },
        {
            "site": "ANYANGCHEON",
            "temperature": 27.5,
            "measuredAt": "2026-05-16T11:00:00Z",
            "weather": {
                "code": 803,
                "description": "튼구름",
                "icon": "04n",
                "temperature": {
                    "actual": 20.64,
                    "feelsLike": 19.93
                },
                "pressure": 1020,
                "humidity": 45,
                "visibility": 10000,
                "windSpeed": 1.29,
                "windDirection": 249,
                "sunrise": 1778876584,
                "sunset": 1778927662
            }
        },
        {
            "site": "JUNGNANGCHEON",
            "temperature": 27.2,
            "measuredAt": "2026-05-16T11:00:00Z",
            "weather": {
                "code": 803,
                "description": "튼구름",
                "icon": "04n",
                "temperature": {
                    "actual": 20.72,
                    "feelsLike": 20.02
                },
                "pressure": 1020,
                "humidity": 45,
                "visibility": 10000,
                "windSpeed": 1.17,
                "windDirection": 270,
                "sunrise": 1778876524,
                "sunset": 1778927655
            }
        },
        {
            "site": "TANCHEON",
            "temperature": 25.1,
            "measuredAt": "2026-05-16T11:00:00Z",
            "weather": {
                "code": 803,
                "description": "튼구름",
                "icon": "04n",
                "temperature": {
                    "actual": 21.14,
                    "feelsLike": 20.43
                },
                "pressure": 1020,
                "humidity": 43,
                "visibility": 10000,
                "windSpeed": 1.32,
                "windDirection": 251,
                "sunrise": 1778876535,
                "sunset": 1778927648
            }
        }
    ]
}