{
    "updatedAt": "2026-07-16T07:00:07.114107017Z",
    "dataCount": 4,
    "temperatures": [
        {
            "site": "SEONYU",
            "temperature": 24.8,
            "measuredAt": "2026-07-16T06:00:00Z",
            "weather": {
                "code": 804,
                "description": "온흐림",
                "icon": "04d",
                "temperature": {
                    "actual": 29.9,
                    "feelsLike": 31.55
                },
                "pressure": 1003,
                "humidity": 54,
                "visibility": 10000,
                "windSpeed": 3.97,
                "windDirection": 267,
                "sunrise": 1784146993,
                "sunset": 1784199190
            }
        },
        {
            "site": "ANYANGCHEON",
            "temperature": 29.3,
            "measuredAt": "2026-07-16T06:00:00Z",
            "weather": {
                "code": 804,
                "description": "온흐림",
                "icon": "04d",
                "temperature": {
                    "actual": 29.34,
                    "feelsLike": 30.67
                },
                "pressure": 1003,
                "humidity": 54,
                "visibility": 10000,
                "windSpeed": 3.58,
                "windDirection": 268,
                "sunrise": 1784147010,
                "sunset": 1784199162
            }
        },
        {
            "site": "JUNGNANGCHEON",
            "temperature": 25.4,
            "measuredAt": "2026-07-16T06:00:00Z",
            "weather": {
                "code": 804,
                "description": "온흐림",
                "icon": "04d",
                "temperature": {
                    "actual": 30.54,
                    "feelsLike": 31.87
                },
                "pressure": 1002,
                "humidity": 50,
                "visibility": 10000,
                "windSpeed": 4.66,
                "windDirection": 272,
                "sunrise": 1784146945,
                "sunset": 1784199156
            }
        },
        {
            "site": "TANCHEON",
            "temperature": 27.0,
            "measuredAt": "2026-07-16T06:00:00Z",
            "weather": {
                "code": 804,
                "description": "온흐림",
                "icon": "04d",
                "temperature": {
                    "actual": 30.56,
                    "feelsLike": 31.91
                },
                "pressure": 1002,
                "humidity": 50,
                "visibility": 10000,
                "windSpeed": 4.51,
                "windDirection": 268,
                "sunrise": 1784146958,
                "sunset": 1784199147
            }
        }
    ]
}