{
    "updatedAt": "2026-04-01T13:00:11.511010874Z",
    "dataCount": 4,
    "temperatures": [
        {
            "site": "SEONYU",
            "temperature": 14.1,
            "measuredAt": "2026-04-01T12:00:00Z",
            "weather": {
                "code": 804,
                "description": "온흐림",
                "icon": "04n",
                "temperature": {
                    "actual": 9.05,
                    "feelsLike": 8.52
                },
                "pressure": 1013,
                "humidity": 66,
                "visibility": 9000,
                "windSpeed": 1.54,
                "windDirection": 200,
                "sunrise": 1774991915,
                "sunset": 1775037239
            }
        },
        {
            "site": "ANYANGCHEON",
            "temperature": 17.0,
            "measuredAt": "2026-04-01T12:00:00Z",
            "weather": {
                "code": 802,
                "description": "구름조금",
                "icon": "03n",
                "temperature": {
                    "actual": 9.82,
                    "feelsLike": 9.82
                },
                "pressure": 1014,
                "humidity": 40,
                "visibility": 10000,
                "windSpeed": 0.51,
                "windDirection": 40,
                "sunrise": 1774991913,
                "sunset": 1775037227
            }
        },
        {
            "site": "JUNGNANGCHEON",
            "temperature": 16.7,
            "measuredAt": "2026-04-01T12:00:00Z",
            "weather": {
                "code": 802,
                "description": "구름조금",
                "icon": "03n",
                "temperature": {
                    "actual": 10.02,
                    "feelsLike": 8.12
                },
                "pressure": 1013,
                "humidity": 40,
                "visibility": 10000,
                "windSpeed": 0.51,
                "windDirection": 40,
                "sunrise": 1774991872,
                "sunset": 1775037199
            }
        },
        {
            "site": "TANCHEON",
            "temperature": 16.7,
            "measuredAt": "2026-04-01T12:00:00Z",
            "weather": {
                "code": 802,
                "description": "구름조금",
                "icon": "03n",
                "temperature": {
                    "actual": 10.06,
                    "feelsLike": 8.17
                },
                "pressure": 1013,
                "humidity": 40,
                "visibility": 10000,
                "windSpeed": 0.51,
                "windDirection": 40,
                "sunrise": 1774991875,
                "sunset": 1775037197
            }
        }
    ]
}